textlab/__init__.py
textlab/classification.py
textlab/mining.py
textlab/process.py
textlab/scrape.py
textlab/similarity.py
textlab/utility.py
TextAnalyticsLab-0.1.2.dist-info/LICENSE
TextAnalyticsLab-0.1.2.dist-info/METADATA
TextAnalyticsLab-0.1.2.dist-info/WHEEL
TextAnalyticsLab-0.1.2.dist-info/top_level.txt
TextAnalyticsLab-0.1.2.dist-info/RECORD
