Metadata-Version: 2.1
Name: TextAnalyticsLab
Version: 0.1.2
Summary: Text Analytics Toolkit (TextAnalyticsLab) for Python
Home-page: https://github.com/sptennak/TextAnalytics
Author: Sumudu Tennakoon
License: Apache License Version 2.0
Platform: UNKNOWN
Classifier: Development Status :: 3 - Alpha
Classifier: Environment :: Console
Classifier: Intended Audience :: Science/Research
Classifier: Intended Audience :: Education
Classifier: Intended Audience :: Developers
Classifier: License :: OSI Approved :: Apache Software License
Classifier: Operating System :: OS Independent
Classifier: Programming Language :: Python
Classifier: Operating System :: OS Independent
Classifier: Topic :: Scientific/Engineering
Classifier: Topic :: Software Development
Requires-Dist: numpy
Requires-Dist: scipy
Requires-Dist: matplotlib
Requires-Dist: pandas
Requires-Dist: pymltoolkit
Requires-Dist: beautifulsoup4
